Workbook

Sheet Ecommerce Orders
A1: 🛒 ECOMMERCE SAMPLE DATASET — hariniselvan-bot.github.io/ecom
A2: Order ID | B2: Order Date | C2: Customer Name | D2: Email | E2: Phone | F2: City | G2: State | H2: Category | I2: Product Name | J2: SKU | K2: Qty | L2: Unit Price (₹) | M2: Total (₹) | N2: Status
A3: ORD-1001 | B3: 2025-01-05 | C3: Priya Ramesh | D3: priya.ramesh@gmail.com | E3: 9876543210 | F3: Chennai | G3: Tamil Nadu | H3: Electronics | I3: boAt Airdopes 141 | J3: BOAT-AIR-141 | K3: 2 | L3: 1299 | M3: =K3*L3 -> 2598 | N3: Delivered
A4: ORD-1002 | B4: 2025-01-08 | C4: Karthik Suresh | D4: karthik.s@yahoo.com | E4: 9123456780 | F4: Coimbatore | G4: Tamil Nadu | H4: Fashion | I4: Levis 511 Slim Jeans | J4: LEV-511-32 | K4: 1 | L4: 3499 | M4: =K4*L4 -> 3499 | N4: Delivered
A5: ORD-1003 | B5: 2025-01-12 | C5: Anitha Balan | D5: anitha.balan@outlook.com | E5: 8765432190 | F5: Bangalore | G5: Karnataka | H5: Home & Kitchen | I5: Prestige Induction Cooktop | J5: PRES-IC-01 | K5: 1 | L5: 2999 | M5: =K5*L5 -> 2999 | N5: Shipped
A6: ORD-1004 | B6: 2025-01-15 | C6: Rajesh Kumar | D6: rajesh.k@gmail.com | E6: 9988776655 | F6: Hyderabad | G6: Telangana | H6: Electronics | I6: Realme Narzo 70 Pro | J6: REAL-N70P | K6: 1 | L6: 17999 | M6: =K6*L6 -> 17999 | N6: Processing
A7: ORD-1005 | B7: 2025-01-18 | C7: Divya Nair | D7: divya.nair@gmail.com | E7: 9870654321 | F7: Kochi | G7: Kerala | H7: Beauty | I7: Lakme CC Cream SPF 30 | J7: LAK-CC-30 | K7: 3 | L7: 299 | M7: =K7*L7 -> 897 | N7: Delivered
A8: ORD-1006 | B8: 2025-01-22 | C8: Sanjay Patel | D8: sanjay.patel@hotmail.com | E8: 9765432108 | F8: Ahmedabad | G8: Gujarat | H8: Sports | I8: Yonex Badminton Racket | J8: YON-BAD-01 | K8: 2 | L8: 1850 | M8: =K8*L8 -> 3700 | N8: Delivered
A9: ORD-1007 | B9: 2025-01-25 | C9: Meena Krishnan | D9: meena.k@gmail.com | E9: 9654321087 | F9: Madurai | G9: Tamil Nadu | H9: Books | I9: Python Programming - O'Reilly | J9: BK-PY-ORL | K9: 1 | L9: 899 | M9: =K9*L9 -> 899 | N9: Delivered
A10: ORD-1008 | B10: 2025-01-28 | C10: Vijay Sharma | D10: vijay.sharma@gmail.com | E10: 9543210876 | F10: Mumbai | G10: Maharashtra | H10: Electronics | I10: Sony WH-1000XM5 Headphones | J10: SONY-WH5 | K10: 1 | L10: 24990 | M10: =K10*L10 -> 24990 | N10: Cancelled
A11: ORD-1009 | B11: 2025-02-02 | C11: Lakshmi Rajan | D11: lakshmi.r@gmail.com | E11: 9432109765 | F11: Trichy | G11: Tamil Nadu | H11: Home & Kitchen | I11: Milton Thermosteel Flask | J11: MIL-TF-1L | K11: 4 | L11: 699 | M11: =K11*L11 -> 2796 | N11: Delivered
A12: ORD-1010 | B12: 2025-02-05 | C12: Suresh Babu | D12: suresh.babu@yahoo.com | E12: 9321098654 | F12: Pune | G12: Maharashtra | H12: Fashion | I12: Nike Air Max 270 | J12: NIK-AM270-9 | K12: 1 | L12: 8999 | M12: =K12*L12 -> 8999 | N12: Shipped
A13: ORD-1011 | B13: 2025-02-09 | C13: Kavitha Raj | D13: kavitha.raj@gmail.com | E13: 9210987543 | F13: Salem | G13: Tamil Nadu | H13: Electronics | I13: Zebronics Bluetooth Speaker | J13: ZEB-BT-100 | K13: 1 | L13: 1299 | M13: =K13*L13 -> 1299 | N13: Delivered
A14: ORD-1012 | B14: 2025-02-12 | C14: Arun Selvam | D14: arun.selvam@outlook.com | E14: 9109876432 | F14: Chennai | G14: Tamil Nadu | H14: Beauty | I14: Dove Body Lotion 400ml | J14: DOV-BL-400 | K14: 2 | L14: 349 | M14: =K14*L14 -> 698 | N14: Delivered
... A22: ORD-1020 | B22: 2025-03-15 | C22: Balaji Ravi | D22: balaji.ravi@gmail.com | E22: 8321097654 | F22: Chennai | G22: Tamil Nadu | H22: Fashion | I22: Van Heusen Formal Shirt | J22: VH-FS-41 | K22: 2 | L22: 1299 | M22: =K22*L22 -> 2598 | N22: Delivered
A23: TOTAL | K23: =SUM(K3:K22) -> 33 | M23: =SUM(M3:M22) -> 149351

Sheet IT Solution Clients
A1: 💻 IT SOLUTION SAMPLE DATASET — mathumuthu.github.io & navaneethan733.github.io
A2: Client ID | B2: Company Name | C2: Contact Person | D2: Email | E2: Phone | F2: City | G2: Service Type | H2: Project Title | I2: Start Date | J2: End Date | K2: Budget (₹) | L2: Status | M2: Rating
A3: CLT-001 | B3: TechNova Pvt Ltd | C3: Arun Kumar | D3: arun.kumar@technova.in | E3: 9876501234 | F3: Chennai | G3: Web Development | H3: Corporate Website Redesign | I3: 2025-01-10 | J3: 2025-03-10 | K3: 180000 | L3: Completed | M3: ★★★★★
A4: CLT-002 | B4: Bright Minds Edu | C4: Preethi Rajan | D4: preethi@brightminds.edu | E4: 9765401233 | F4: Coimbatore | G4: Mobile App | H4: Student Learning App (Android+iOS) | I4: 2025-01-15 | J4: 2025-04-30 | K4: 350000 | L4: In Progress | M4: ★★★★☆
A5: CLT-003 | B5: GreenEarth Agri | C5: Selvam Murugan | D5: selvam@greenearth.co | E5: 9654301232 | F5: Madurai | G5: ERP Solution | H5: Farm Management ERP | I5: 2025-02-01 | J5: 2025-06-30 | K5: 520000 | L5: In Progress | M5: ★★★★☆
A6: CLT-004 | B6: FinEdge Capital | C6: Ramya Subramanian | D6: ramya.s@finedge.com | E6: 9543201231 | F6: Bangalore | G6: Cybersecurity | H6: Network Security Audit & Setup | I6: 2025-02-10 | J6: 2025-03-10 | K6: 95000 | L6: Completed | M6: ★★★★★
A7: CLT-005 | B7: MediCare Clinic | C7: Dr. Sathish Bose | D7: sathish.b@medicare.in | E7: 9432101230 | F7: Hyderabad | G7: Web Development | H7: Online Appointment Portal | I7: 2025-02-15 | J7: 2025-04-15 | K7: 140000 | L7: Completed | M7: ★★★★☆
A8: CLT-006 | B8: LogiTrack Ltd | C8: Naveen Pillai | D8: naveen.p@logitrack.in | E8: 9321001229 | F8: Kochi | G8: Cloud Services | H8: AWS Migration & DevOps Setup | I8: 2025-03-01 | J8: 2025-05-31 | K8: 680000 | L8: In Progress | M8: ★★★★★
A9: CLT-007 | B9: RetailX Store | C9: Divya Chandran | D9: divya.c@retailx.com | E9: 9210901228 | F9: Chennai | G9: E-Commerce | H9: Shopify Custom Store + Payment Gateway | I9: 2025-03-05 | J9: 2025-04-05 | K9: 210000 | L9: Completed | M9: ★★★★★
A10: CLT-008 | B10: BuildPro Constructions | C10: Manoj Iyer | D10: manoj.i@buildpro.in | E10: 9109801227 | F10: Pune | G10: Mobile App | H10: Project Site Management App | I10: 2025-03-10 | J10: 2025-06-10 | K10: 290000 | L10: In Progress | M10: ★★★☆☆
A11: CLT-009 | B11: HRLinks Solutions | C11: Kavitha Nair | D11: kavitha.n@hrlinks.com | E11: 9008701226 | F11: Mumbai | G11: SaaS Development | H11: HR & Payroll SaaS Platform | I11: 2025-03-15 | J11: 2025-09-15 | K11: 950000 | L11: In Progress | M11: ★★★★☆
A12: CLT-010 | B12: FoodieHub | C12: Balaji Venkat | D12: balaji.v@foodiehub.in | E12: 8987601225 | F12: Trichy | G12: Web Development | H12: Food Delivery Website + Admin Panel | I12: 2025-03-20 | J12: 2025-05-20 | K12: 175000 | L12: In Progress | M12: ★★★★☆
A13: CLT-011 | B13: SmartLearn Academy | C13: Asha Krishnan | D13: asha.k@smartlearn.edu | E13: 8876501224 | F13: Salem | G13: Mobile App | H13: Quiz & Exam App with Analytics | I13: 2025-04-01 | J13: 2025-07-01 | K13: 320000 | L13: Planned | M13: N/A
A14: CLT-012 | B14: AutoDrive Rentals | C14: Suresh Raja | D14: suresh.r@autodrive.in | E14: 8765401223 | F14: Delhi | G14: ERP Solution | H14: Fleet & Booking Management ERP | I14: 2025-04-05 | J14: 2025-08-05 | K14: 480000 | L14: Planned | M14: N/A
... A22: CLT-020 | B22: CropSense AgriTech | C22: Rajesh Pandian | D22: rajesh.p@cropsense.in | E22: 7987601215 | F22: Madurai | G22: Mobile App | H22: IoT-Based Crop Monitoring App | I22: 2025-05-15 | J22: 2025-10-15 | K22: 620000 | L22: Planned | M22: N/A
A23: TOTAL | K23: =SUM(K3:K22) -> 8290000

Sheet Summary Dashboard
A1: 📊 SAMPLE DATA SUMMARY DASHBOARD
A2: 🛒 ECOMMERCE METRICS
A3: Total Orders | B3: =COUNTA('Ecommerce Orders'!A3:A22) -> 20
A4: Total Revenue (₹) | B4: =SUM('Ecommerce Orders'!M3:M22) -> 149351
A5: Avg Order Value (₹) | B5: =AVERAGE('Ecommerce Orders'!M3:M22) -> 7467.55
A6: Delivered Orders | B6: =COUNTIF('Ecommerce Orders'!N3:N22,"Delivered") -> 13
A7: Cancelled / Returned | B7: =COUNTIF('Ecommerce Orders'!N3:N22,"Cancelled")+COUNTIF('Ecommerce Orders'!N3:N22,"Returned") -> 2
A9: 💻 IT SOLUTION METRICS
A10: Total Clients | B10: =COUNTA('IT Solution Clients'!A3:A22) -> 20
A11: Total Project Budget (₹) | B11: =SUM('IT Solution Clients'!K3:K22) -> 8290000
A12: Avg Project Budget (₹) | B12: =AVERAGE('IT Solution Clients'!K3:K22) -> 414500
A13: Completed Projects | B13: =COUNTIF('IT Solution Clients'!L3:L22,"Completed") -> 4
A14: In Progress Projects | B14: =COUNTIF('IT Solution Clients'!L3:L22,"In Progress") -> 8
A15: Planned Projects | B15: =COUNTIF('IT Solution Clients'!L3:L22,"Planned") -> 8
